chain/__init__.py
chain_call-0.1.1.dist-info/DESCRIPTION.rst
chain_call-0.1.1.dist-info/METADATA
chain_call-0.1.1.dist-info/RECORD
chain_call-0.1.1.dist-info/WHEEL
chain_call-0.1.1.dist-info/entry_points.txt
chain_call-0.1.1.dist-info/metadata.json
chain_call-0.1.1.dist-info/top_level.txt
