Metadata-Version: 2.0
Name: chain-call
Version: 0.1.1
Summary: Call a function with a chain
Home-page: UNKNOWN
Author: Yixian Du
Author-email: UNKNOWN
License: MIT
Keywords: chain
Platform: UNKNOWN
Classifier: Programming Language :: Python :: 3
Classifier: Programming Language :: Python :: 3.3
Classifier: Programming Language :: Python :: 3.4
Classifier: Programming Language :: Python :: 3.5
